{
  "name": "Maurício Marcelino",
  "photo": "https://avatars.githubusercontent.com/u/94411600?v=4",
  "job": "Desenvolvedor Fullstack",
  "location": "São Paulo - SP",
  "phone": "(11) 98054-1071",
  "email": "marcosmauricio1299@gmail.com",
  "skills": {
    "hardSkills": [
      {
        "name": "dotNet",
        "logo": "https://raw.githubusercontent.com/marcostwelve/personal-portfolio/refs/heads/main/src/assets/svg/tools/dotnet.svg"
      },
      {
        "name": "Nodejs",
        "logo": "https://raw.githubusercontent.com/marcostwelve/personal-portfolio/refs/heads/main/src/assets/svg/tools/nodejs.svg"
      },
      {
        "name": "Angular",
        "logo": "https://raw.githubusercontent.com/marcostwelve/personal-portfolio/refs/heads/main/src/assets/svg/tools/angular.svg"
      },
      {
        "name": "React",
        "logo": "https://raw.githubusercontent.com/marcostwelve/personal-portfolio/refs/heads/main/src/assets/svg/tools/react.svg"
      },
      {
        "name": "Postgresql",
        "logo": "https://raw.githubusercontent.com/marcostwelve/personal-portfolio/refs/heads/main/src/assets/svg/tools/postgresql.svg"
      },
      {
        "name": "Aws",
        "logo": "https://raw.githubusercontent.com/marcostwelve/personal-portfolio/refs/heads/main/src/assets/svg/tools/aws.svg"
      }
    ],
    "softSkills": [
      "Empatia",
      "Facilidade em aprender",
      "Flexibilidade",
      "Organização",
      "Trabalho em equipe"
    ]
  },
  "languages": [
    "Português BR",
    "Inglês (intermediário)"
  ],
  "portfolio": [
    {
      "name": "Crud full Stack em ASP.net",
      "url": "https://github.com/marcostwelve/crudStoredProcedure",
      "github": true
    },
    {
      "name": "API cadastro de Clientes em .net Core",
      "url": "https://github.com/marcostwelve/api-clientes",
      "github": true
    },
    {
      "name": "API Identity em .net Core",
      "url": "https://github.com/marcostwelve/apiIdentity",
      "github": true
    },
    {
      "name": "API dicionário em .net Core",
      "url": "https://github.com/marcostwelve/dictionaryAPI",
      "github": true
    },
    {
      "name": "TODO com Angular",
      "url": "https://github.com/marcostwelve/memoteca",
      "github": true
    },
    {
      "name": "Gerador de CPF com Angular",
      "url": "https://gerador-cpf-sigma.vercel.app/login",
      "github": true
    },
    {
      "name": "Gerador de paleta de cores",
      "url": "https://marcostwelve.github.io/paleteColors/",
      "github": true
    },
    {
      "name": "API em Java e Springboot",
      "url": "https://github.com/marcostwelve/beneficiario-api",
      "github": true
    }
  ],
  "professionalExperience": [
    {
      "name": "Desenvolvedor Full Stack / Viceri Seidor",
      "period": "2024 - até o momento",
      "description": "Desenvolvimento de projetos e sustentação nos sistemas legados, alocado no cliente de valores."
    },
    {
      "name": "Desenvolvedor Full Stack / Hospital das Clínicas",
      "period": "2022 - 2024",
      "description": "Desenvolvimento de projetos e sustentação nos sistemas legados de todo o hospital das Clínicas."
    }
  ]
}